{
	"format_version": "1.8.0",
	"animations": {
		"idle": {
			"loop": true,
			"animation_length": 3,
			"bones": {
				"BODY": {
					"rotation": {
						"0.0": {
							"vector": [0, 0, 0],
							"easing": "linear"
						},
						"0.75": {
							"vector": [-1.5, 0, 0],
							"easing": "linear"
						},
						"1.5": {
							"vector": [0, 0, 0],
							"easing": "linear"
						},
						"2.25": {
							"vector": [-1.5, 0, 0],
							"easing": "linear"
						},
						"3.0": {
							"vector": [0, 0, 0],
							"easing": "linear"
						}
					}
				},
				"HEAD": {
					"rotation": {
						"0.0": {
							"vector": [0, 4.5, 0],
							"easing": "linear"
						},
						"0.3": {
							"vector": [0, 4.5, 0],
							"easing": "linear"
						},
						"0.55": {
							"vector": [0, 11.5, 0],
							"easing": "linear"
						},
						"1.0": {
							"vector": [0, 11.5, 0],
							"easing": "linear"
						},
						"1.2": {
							"vector": [0, -7.88542, 0],
							"easing": "linear"
						},
						"1.45": {
							"vector": [0, -7.88542, 0],
							"easing": "linear"
						},
						"1.6": {
							"vector": [0, -13.89, 0],
							"easing": "linear"
						},
						"1.8": {
							"vector": [0, -13.88542, 0],
							"easing": "linear"
						},
						"2.0": {
							"vector": [0, -18.53828, 0],
							"easing": "linear"
						},
						"2.5": {
							"vector": [0, -18.53828, 0],
							"easing": "linear"
						},
						"2.65": {
							"vector": [0, -0.5, 0],
							"easing": "linear"
						},
						"2.9": {
							"vector": [0, -0.5, 0],
							"easing": "linear"
						},
						"3.0": {
							"vector": [0, 4.5, 0],
							"easing": "linear"
						}
					}
				},
				"L_Wing": {
					"rotation": {
						"0.0": {
							"vector": [-1.5, -15.5, -2.5],
							"easing": "linear"
						},
						"0.7": {
							"vector": [-5, -15.5, -7.5],
							"easing": "linear"
						},
						"1.45": {
							"vector": [-1.5, -15.5, -2.5],
							"easing": "linear"
						},
						"2.2": {
							"vector": [-5, -15.5, -7.5],
							"easing": "linear"
						},
						"3.0": {
							"vector": [-1.5, -15.5, -2.5],
							"easing": "linear"
						}
					}
				},
				"bone4": {
					"rotation": {
						"0.0": {
							"vector": [24.5, 0, 0],
							"easing": "linear"
						},
						"0.25": {
							"vector": [24.5, 0, 0],
							"easing": "linear"
						},
						"0.75": {
							"vector": [17, 0, 0],
							"easing": "linear"
						},
						"1.75": {
							"vector": [17, 0, 0],
							"easing": "linear"
						},
						"3.0": {
							"vector": [24.5, 0, 0],
							"easing": "linear"
						}
					}
				},
				"TAIL": {
					"rotation": {
						"0.0": {
							"vector": [-21, 0, 0],
							"easing": "linear"
						},
						"0.15": {
							"vector": [-21.23242, 11.84608, 0],
							"easing": "linear"
						},
						"0.2": {
							"vector": [-21.23242, -12.15392, 0],
							"easing": "linear"
						},
						"0.3": {
							"vector": [-21.23242, 11.84608, 0],
							"easing": "linear"
						},
						"0.4": {
							"vector": [-21.23242, -12.15392, 0],
							"easing": "linear"
						},
						"0.45": {
							"vector": [-21.23242, 11.84608, 0],
							"easing": "linear"
						},
						"0.55": {
							"vector": [-21.23242, -12.15392, 0],
							"easing": "linear"
						},
						"0.65": {
							"vector": [-21.23242, 11.84608, 0],
							"easing": "linear"
						},
						"0.75": {
							"vector": [-21, 0, 0],
							"easing": "linear"
						},
						"1.3": {
							"vector": [-17, 0, 0],
							"easing": "linear"
						},
						"1.9": {
							"vector": [-21, 0, 0],
							"easing": "linear"
						},
						"2.4": {
							"vector": [-17, 0, 0],
							"easing": "linear"
						},
						"3.0": {
							"vector": [-21, 0, 0],
							"easing": "linear"
						}
					}
				},
				"R_Wing": {
					"rotation": {
						"0.0": {
							"vector": [-1.5, 15.5, 2.5],
							"easing": "linear"
						},
						"0.7": {
							"vector": [-5, 15.5, 7.5],
							"easing": "linear"
						},
						"1.45": {
							"vector": [-1.5, 15.5, 2.5],
							"easing": "linear"
						},
						"2.2": {
							"vector": [-5, 15.5, 7.5],
							"easing": "linear"
						},
						"3.0": {
							"vector": [-1.5, 15.5, 2.5],
							"easing": "linear"
						}
					}
				},
				"bone8": {
					"rotation": {
						"0.0": {
							"vector": [24.5, 0, 0],
							"easing": "linear"
						},
						"0.25": {
							"vector": [24.5, 0, 0],
							"easing": "linear"
						},
						"0.75": {
							"vector": [17, 0, 0],
							"easing": "linear"
						},
						"1.75": {
							"vector": [17, 0, 0],
							"easing": "linear"
						},
						"3.0": {
							"vector": [24.5, 0, 0],
							"easing": "linear"
						}
					}
				}
			}
		},
		"sleep": {
			"loop": true,
			"animation_length": 2,
			"bones": {
				"MAIN": {
					"rotation": {
						"vector": [75, 0, 0],
						"easing": "linear"
					},
					"position": {
						"vector": [0, 1.4, 7],
						"easing": "linear"
					}
				},
				"BODY": {
					"rotation": {
						"vector": [-15, 0, 0],
						"easing": "linear"
					}
				},
				"bone5": {
					"rotation": {
						"vector": [-2.5, 0, 0],
						"easing": "linear"
					}
				},
				"bone": {
					"rotation": {
						"vector": [12.5, 0, 0],
						"easing": "linear"
					},
					"position": {
						"vector": [0, -1.5473, -1.1383],
						"easing": "linear"
					}
				},
				"HEAD": {
					"rotation": {
						"0.0": {
							"vector": [-70, 0, 0],
							"easing": "linear"
						},
						"1.0": {
							"vector": [-67.5, 0, 0],
							"easing": "linear"
						},
						"2.0": {
							"vector": [-70, 0, 0],
							"easing": "linear"
						}
					},
					"position": {
						"vector": [0, -0.2416, 1.828],
						"easing": "linear"
					}
				},
				"L_Wing": {
					"rotation": {
						"vector": [1.44519, -26.98407, -8.23787],
						"easing": "linear"
					}
				},
				"bone4": {
					"rotation": {
						"vector": [22.5, 0, 0],
						"easing": "linear"
					}
				},
				"R_Wing": {
					"rotation": {
						"vector": [1.44519, 26.98407, 8.23787],
						"easing": "linear"
					}
				},
				"bone8": {
					"rotation": {
						"vector": [22.5, 0, 0],
						"easing": "linear"
					}
				},
				"TAIL": {
					"rotation": {
						"vector": [-20, 0, 0],
						"easing": "linear"
					}
				},
				"L_LEG": {
					"rotation": {
						"vector": [-5, 0, 0],
						"easing": "linear"
					},
					"position": {
						"vector": [0, 2.7412, -0.9659],
						"easing": "linear"
					}
				},
				"bone6": {
					"rotation": {
						"vector": [30, 0, 0],
						"easing": "linear"
					}
				},
				"bone7": {
					"rotation": {
						"vector": [77.5, 0, 0],
						"easing": "linear"
					}
				},
				"R_LEG": {
					"rotation": {
						"vector": [-5, 0, 0],
						"easing": "linear"
					},
					"position": {
						"vector": [0, 2.7412, -0.9659],
						"easing": "linear"
					}
				},
				"bone9": {
					"rotation": {
						"vector": [30, 0, 0],
						"easing": "linear"
					}
				},
				"bone10": {
					"rotation": {
						"vector": [77.5, 0, 0],
						"easing": "linear"
					}
				}
			}
		},
		"swim": {
			"loop": true,
			"animation_length": 4,
			"bones": {
				"MAIN": {
					"rotation": {
						"0.0": {
							"vector": [75, 0, 0]
						},
						"0.75": {
							"vector": [75, 0, 0]
						}
					},
					"position": {
						"0.0": {
							"vector": [0, -3.2, 14]
						},
						"0.25": {
							"vector": [0, -3.35, 14]
						},
						"0.75": {
							"vector": [0, -3, 14]
						},
						"1.25": {
							"vector": [0, -3.35, 14]
						},
						"1.75": {
							"vector": [0, -3, 14]
						},
						"2.25": {
							"vector": [0, -3.35, 14]
						},
						"2.75": {
							"vector": [0, -3, 14]
						},
						"3.25": {
							"vector": [0, -3.35, 14]
						},
						"3.75": {
							"vector": [0, -3, 14]
						},
						"4.0": {
							"vector": [0, -3.2, 14]
						}
					}
				},
				"bone5": {
					"rotation": {
						"vector": [-7.5, 0, 0]
					},
					"position": {
						"vector": [0, -0.14092, -0.17362]
					}
				},
				"HEAD": {
					"rotation": {
						"0.0": {
							"vector": [-22.5, 0, 0]
						},
						"0.25": {
							"vector": [-22.5, 0, 0]
						},
						"0.3333": {
							"vector": [-22.5, 12.5, 0]
						},
						"0.5417": {
							"vector": [-22.5, 12.5, 0]
						},
						"0.625": {
							"vector": [-22.5, 27.05, 0]
						},
						"0.9583": {
							"vector": [-22.5, 27.05, 0]
						},
						"1.1667": {
							"vector": [-22.5, 0, 0]
						},
						"2.0833": {
							"vector": [-22.5, 0, 0]
						},
						"2.1667": {
							"vector": [-22.5, -17.5, 0]
						},
						"2.3333": {
							"vector": [-22.5, -17.5, 0]
						},
						"2.4167": {
							"vector": [-42.5, -10.5, 0]
						},
						"2.9583": {
							"vector": [-42.5, -10.5, 0]
						},
						"3.0417": {
							"vector": [-39.64, 16, 0]
						},
						"3.2917": {
							"vector": [-39.64, 16, 0]
						},
						"3.5417": {
							"vector": [-22.5, 0, 0]
						}
					},
					"position": {
						"vector": [0, 0.908, 1.63606]
					}
				},
				"TAIL": {
					"rotation": {
						"0.0": {
							"vector": [-29, 0, 0]
						},
						"0.875": {
							"vector": [-29, 0, 0]
						},
						"1.0": {
							"vector": [-29.23242, -2.15392, 12.31594]
						},
						"1.0833": {
							"vector": [-29.23242, -2.15392, -12.3159]
						},
						"1.1667": {
							"vector": [-29.23242, -2.15392, 12.31594]
						},
						"1.25": {
							"vector": [-29.23242, -2.15392, -12.3159]
						},
						"1.3333": {
							"vector": [-29.23242, -2.15392, 12.31594]
						},
						"1.4167": {
							"vector": [-29.23242, -2.15392, -12.3159]
						},
						"1.5": {
							"vector": [-29.23242, -2.15392, 12.31594]
						},
						"1.625": {
							"vector": [-29, 0, 0]
						},
						"3.0": {
							"vector": [-29, 0, 0]
						}
					},
					"position": {
						"vector": [0, 1.41737, -0.06761]
					}
				},
				"L_Wing": {
					"rotation": {
						"0.0": {
							"vector": [-36, -64, 10]
						},
						"0.25": {
							"vector": [-36, -64, 10]
						},
						"0.4167": {
							"vector": [-36, -50.5, 10]
						},
						"0.5833": {
							"vector": [-36, -70.5, 10]
						},
						"0.75": {
							"vector": [-36, -50.5, 10]
						},
						"0.9167": {
							"vector": [-36, -64, 10]
						},
						"1.25": {
							"vector": [-36, -64, 10]
						},
						"1.4167": {
							"vector": [-36, -50.5, 10]
						},
						"1.5833": {
							"vector": [-36, -70.5, 10]
						},
						"1.75": {
							"vector": [-36, -64, 10]
						},
						"2.0": {
							"vector": [-36, -64, 10]
						},
						"2.1667": {
							"vector": [-36, -50.5, 10]
						},
						"2.3333": {
							"vector": [-36, -70.5, 10]
						},
						"2.5": {
							"vector": [-36, -50.5, 10]
						},
						"2.6667": {
							"vector": [-36, -70.5, 10]
						},
						"2.8333": {
							"vector": [-36, -50.5, 10]
						},
						"3.0": {
							"vector": [-36, -70.5, 10]
						},
						"3.1667": {
							"vector": [-36, -64, 10]
						},
						"3.5": {
							"vector": [-36, -64, 10]
						},
						"3.6667": {
							"vector": [-36, -50.5, 10]
						},
						"3.8333": {
							"vector": [-36, -70.5, 10]
						},
						"4.0": {
							"vector": [-36, -64, 10]
						}
					},
					"position": {
						"vector": [0, 0, 0]
					}
				},
				"bone3": {
					"rotation": {
						"vector": [-10, 0, 0]
					}
				},
				"R_LEG": {
					"rotation": {
						"0.0": {
							"vector": [15, 0, 5]
						},
						"0.5": {
							"vector": [12.5, 0, 5]
						},
						"1.0": {
							"vector": [15, 0, 5]
						},
						"1.5": {
							"vector": [12.5, 0, 5]
						},
						"2.0": {
							"vector": [15, 0, 5]
						},
						"2.5": {
							"vector": [12.5, 0, 5]
						},
						"3.0": {
							"vector": [15, 0, 5]
						},
						"3.5": {
							"vector": [12.5, 0, 5]
						},
						"4.0": {
							"vector": [15, 0, 5]
						}
					}
				},
				"bone16": {
					"rotation": {
						"0.0": {
							"vector": [90, 0, 0]
						},
						"0.25": {
							"vector": [95.17, 0, 0]
						},
						"0.75": {
							"vector": [85, 0, 0]
						},
						"1.25": {
							"vector": [95.17, 0, 0]
						},
						"1.75": {
							"vector": [85, 0, 0]
						},
						"2.25": {
							"vector": [95.17, 0, 0]
						},
						"2.75": {
							"vector": [85, 0, 0]
						},
						"3.25": {
							"vector": [95.17, 0, 0]
						},
						"3.75": {
							"vector": [85, 0, 0]
						},
						"4.0": {
							"vector": [90, 0, 0]
						}
					}
				},
				"bone15": {
					"rotation": {
						"0.0": {
							"vector": [7.5, 0, 0]
						},
						"3.0": {
							"vector": [7.5, 0, 0]
						}
					}
				},
				"L_LEG": {
					"rotation": {
						"0.0": {
							"vector": [15, 0, -5]
						},
						"0.5": {
							"vector": [12.5, 0, -5]
						},
						"1.0": {
							"vector": [15, 0, -5]
						},
						"1.5": {
							"vector": [12.5, 0, -5]
						},
						"2.0": {
							"vector": [15, 0, -5]
						},
						"2.5": {
							"vector": [12.5, 0, -5]
						},
						"3.0": {
							"vector": [15, 0, -5]
						},
						"3.5": {
							"vector": [12.5, 0, -5]
						},
						"4.0": {
							"vector": [15, 0, -5]
						}
					}
				},
				"bone6": {
					"rotation": {
						"0.0": {
							"vector": [7.5, 0, 0]
						},
						"3.0": {
							"vector": [7.5, 0, 0]
						}
					}
				},
				"bone7": {
					"rotation": {
						"0.0": {
							"vector": [90, 0, 0]
						},
						"0.25": {
							"vector": [95.17, 0, 0]
						},
						"0.75": {
							"vector": [85, 0, 0]
						},
						"1.25": {
							"vector": [95.17, 0, 0]
						},
						"1.75": {
							"vector": [85, 0, 0]
						},
						"2.25": {
							"vector": [95.17, 0, 0]
						},
						"2.75": {
							"vector": [85, 0, 0]
						},
						"3.25": {
							"vector": [95.17, 0, 0]
						},
						"3.75": {
							"vector": [85, 0, 0]
						},
						"4.0": {
							"vector": [90, 0, 0]
						}
					}
				},
				"R_Wing": {
					"rotation": {
						"0.0": {
							"vector": [-36, 64, -10]
						},
						"0.25": {
							"vector": [-36, 64, -10]
						},
						"0.4167": {
							"vector": [-36, 50.5, -10]
						},
						"0.5833": {
							"vector": [-36, 70.5, -10]
						},
						"0.75": {
							"vector": [-36, 50.5, -10]
						},
						"0.9167": {
							"vector": [-36, 64, -10]
						},
						"1.25": {
							"vector": [-36, 64, -10]
						},
						"1.4167": {
							"vector": [-36, 50.5, -10]
						},
						"1.5833": {
							"vector": [-36, 70.5, -10]
						},
						"1.75": {
							"vector": [-36, 64, -10]
						},
						"2.0": {
							"vector": [-36, 64, -10]
						},
						"2.1667": {
							"vector": [-36, 50.5, -10]
						},
						"2.3333": {
							"vector": [-36, 70.5, -10]
						},
						"2.5": {
							"vector": [-36, 50.5, -10]
						},
						"2.6667": {
							"vector": [-36, 70.5, -10]
						},
						"2.8333": {
							"vector": [-36, 50.5, -10]
						},
						"3.0": {
							"vector": [-36, 70.5, -10]
						},
						"3.1667": {
							"vector": [-36, 64, -10]
						},
						"3.5": {
							"vector": [-36, 64, -10]
						},
						"3.6667": {
							"vector": [-36, 50.5, -10]
						},
						"3.8333": {
							"vector": [-36, 70.5, -10]
						},
						"4.0": {
							"vector": [-36, 64, -10]
						}
					},
					"position": {
						"vector": [0, 0, 0]
					}
				},
				"bone8": {
					"rotation": {
						"vector": [-10, 0, 0]
					}
				},
				"BODY": {
					"rotation": {
						"vector": [-12.5, 0, 0]
					}
				},
				"bone": {
					"rotation": {
						"vector": [-45, 0, 0]
					},
					"position": {
						"vector": [0, 0.46138, 0.79821]
					}
				},
				"bone10": {
					"rotation": {
						"vector": [95, 0, 0]
					}
				}
			}
		},
		"walk": {
			"loop": true,
			"animation_length": 0.6667,
			"bones": {
				"BODY": {
					"rotation": {
						"0.0": {
							"vector": [5, 0, 0],
							"easing": "linear"
						},
						"0.1667": {
							"vector": [4.8423, 2.55868, -5.05239],
							"easing": "linear"
						},
						"0.3333": {
							"vector": [5, 0, 0],
							"easing": "linear"
						},
						"0.5": {
							"vector": [4.8423, -2.55868, 5.05239],
							"easing": "linear"
						},
						"0.6667": {
							"vector": [5, 0, 0],
							"easing": "linear"
						}
					},
					"position": {
						"0.0": {
							"vector": [0, 0, 0],
							"easing": "linear"
						},
						"0.1667": {
							"vector": [0, -0.25, 0],
							"easing": "linear"
						}
					}
				},
				"bone5": {
					"rotation": {
						"vector": ["linear", "linear", "linear"]
					}
				},
				"HEAD": {
					"rotation": {
						"0.0": {
							"vector": [-29.93855, 6.05302, -7.10708],
							"easing": "linear"
						},
						"0.3333": {
							"vector": [-29.93855, -6.05302, 7.10708],
							"easing": "linear"
						},
						"0.6667": {
							"vector": [-29.93855, 6.05302, -7.10708],
							"easing": "linear"
						}
					}
				},
				"L_Wing": {
					"rotation": {
						"vector": ["linear", "linear", "linear"]
					}
				},
				"bone3": {
					"rotation": {
						"vector": ["linear", "linear", "linear"]
					}
				},
				"R_Wing": {
					"rotation": {
						"vector": ["linear", "linear", "linear"]
					}
				},
				"bone8": {
					"rotation": {
						"vector": ["linear", "linear", "linear"]
					}
				},
				"TAIL": {
					"rotation": {
						"vector": ["linear", "linear", "linear"]
					},
					"position": {
						"vector": ["linear", "linear", "linear"]
					}
				},
				"L_LEG": {
					"rotation": {
						"0.0": {
							"vector": [0, 0, 0],
							"easing": "linear"
						},
						"0.1667": {
							"vector": [-17.5, 0, 0],
							"easing": "linear"
						},
						"0.3333": {
							"vector": [0, 0, 0],
							"easing": "linear"
						},
						"0.5": {
							"vector": [35, 0, 0],
							"easing": "linear"
						},
						"0.6667": {
							"vector": [0, 0, 0],
							"easing": "linear"
						}
					},
					"position": {
						"0.0": {
							"vector": [0, 0, 0],
							"easing": "linear"
						},
						"0.1667": {
							"vector": [0, 0.48, 0],
							"easing": "linear"
						},
						"0.5": {
							"vector": [0, -0.8, 0],
							"easing": "linear"
						},
						"0.6667": {
							"vector": [0, 0, 0],
							"easing": "linear"
						}
					}
				},
				"bone6": {
					"rotation": {
						"0.0": {
							"vector": [-38.33, 0, 0],
							"easing": "linear"
						},
						"0.25": {
							"vector": [5, 0, 0],
							"easing": "linear"
						},
						"0.3333": {
							"vector": [0, 0, 0],
							"easing": "linear"
						},
						"0.4167": {
							"vector": [-11.25, 0, 0],
							"easing": "linear"
						},
						"0.5": {
							"vector": [-12.5, 0, 0],
							"easing": "linear"
						},
						"0.6667": {
							"vector": [-38.33, 0, 0],
							"easing": "linear"
						}
					}
				},
				"bone7": {
					"rotation": {
						"0.0": {
							"vector": [-4, 0, 0],
							"easing": "linear"
						},
						"0.1667": {
							"vector": [5.83, 0, 0],
							"easing": "linear"
						},
						"0.3333": {
							"vector": [0, 0, 0],
							"easing": "linear"
						},
						"0.5": {
							"vector": [-12.5, 0, 0],
							"easing": "linear"
						},
						"0.6667": {
							"vector": [-4, 0, 0],
							"easing": "linear"
						}
					}
				},
				"R_LEG": {
					"rotation": {
						"0.0": {
							"vector": [0, 0, 0],
							"easing": "linear"
						},
						"0.1667": {
							"vector": [35, 0, 0],
							"easing": "linear"
						},
						"0.3333": {
							"vector": [0, 0, 0],
							"easing": "linear"
						},
						"0.5": {
							"vector": [-17.5, 0, 0],
							"easing": "linear"
						},
						"0.6667": {
							"vector": [0, 0, 0],
							"easing": "linear"
						}
					},
					"position": {
						"0.0": {
							"vector": [0, 0, 0],
							"easing": "linear"
						},
						"0.1667": {
							"vector": [0, -0.8, 0],
							"easing": "linear"
						},
						"0.5": {
							"vector": [0, 0.48, 0],
							"easing": "linear"
						},
						"0.6667": {
							"vector": [0, 0, 0],
							"easing": "linear"
						}
					}
				},
				"bone15": {
					"rotation": {
						"0.0": {
							"vector": [0, 0, 0],
							"easing": "linear"
						},
						"0.0833": {
							"vector": [-11.25, 0, 0],
							"easing": "linear"
						},
						"0.1667": {
							"vector": [-12.5, 0, 0],
							"easing": "linear"
						},
						"0.3333": {
							"vector": [-38.33, 0, 0],
							"easing": "linear"
						},
						"0.5833": {
							"vector": [5, 0, 0],
							"easing": "linear"
						},
						"0.6667": {
							"vector": [0, 0, 0],
							"easing": "linear"
						}
					}
				},
				"bone16": {
					"rotation": {
						"0.0": {
							"vector": [0, 0, 0],
							"easing": "linear"
						},
						"0.1667": {
							"vector": [-12.5, 0, 0],
							"easing": "linear"
						},
						"0.5": {
							"vector": [5.83, 0, 0],
							"easing": "linear"
						},
						"0.6667": {
							"vector": [0, 0, 0],
							"easing": "linear"
						}
					}
				}
			}
		}
	},
	"geckolib_format_version": 2
}